pydms/__init__.py
pydms/env.py
pydms/main.py
pydms/clitools/__init__.py
pydms/clitools/cli.py
pydms/consul_client/__init__.py
pydms/consul_client/consul_client.py
pydms/data/__init__.py
pydms/data/modules/README.md
pydms/data/modules/__init__.py
pydms/data/modules/consul/__init__.py
pydms/data/modules/consul/consul-demo.py
pydms/data/modules/consul/consul.md
pydms/data/modules/consul/docker-compose-demo.yaml
pydms/data/modules/consul/docker-compose-old.yaml
pydms/data/modules/consul/docker-compose.yaml
pydms/data/modules/filebrowser/docker-compose.yaml
pydms/data/modules/kong/docker-compose-2.yaml
pydms/data/modules/kong/docker-compose.yaml
pydms/data/modules/kong/init-kong.sh
pydms/data/modules/kong/kong.md
pydms/data/modules/kong/start-kong.sh
pydms/data/modules/kong/test-kong.py
pydms/data/modules/mongodb/docker-compose.yaml
pydms/data/modules/nginx/docker-compose.yaml
pydms/data/modules/nginx/ngnix.md
pydms/data/modules/rabbitmq/README.md
pydms/data/modules/rabbitmq/demo-get.py
pydms/data/modules/rabbitmq/demo-send.py
pydms/data/modules/rabbitmq/demo.py
pydms/data/modules/rabbitmq/docker-compose.yaml
pydms/data/modules/registrator/docker-compose.yaml
pydms/data/modules/registrator/registrator.md
pydms-0.0.1.7.dist-info/LICENSE
pydms-0.0.1.7.dist-info/METADATA
pydms-0.0.1.7.dist-info/WHEEL
pydms-0.0.1.7.dist-info/entry_points.txt
pydms-0.0.1.7.dist-info/top_level.txt
pydms-0.0.1.7.dist-info/RECORD
