Metadata-Version: 2.1
Name: pydms
Version: 0.0.1.7
Summary: python distributed micro-services building tools.
Home-page: http://github.com/Peiiii/pydms
Author: Wang Pei
Author-email: 1535376447@qq.com
License: UNKNOWN
Platform: UNKNOWN
Classifier: Programming Language :: Python :: 3
Classifier: License :: OSI Approved :: MIT License
Classifier: Operating System :: OS Independent
Requires-Python: >=3.0
Requires-Dist: fire
